{"kajaNormabell":{"firstName":"Kaja","lastName":"Normabell","lat":52.5191353177,"long":13.3575357558,"personalityType":"ESFP","gender":"women"},"ruddyMonnery":{"firstName":"Ruddy","lastName":"Monnery","lat":52.5508338707,"long":13.3924413533,"personalityType":"ESTP","gender":"women"},"oralieSkittles":{"firstName":"Oralie","lastName":"Skittles","lat":52.5163780989,"long":13.5036765343,"personalityType":"ESTJ","gender":"o"},"delphineBrunskill":{"firstName":"Delphine","lastName":"Brunskill","lat":52.5201435014,"long":13.3975457067,"personalityType":"ENFJ","gender":"women"},"kettyEde":{"firstName":"Ketty","lastName":"Ede","lat":52.5271690625,"long":13.4823012415,"personalityType":"ISFP","gender":"men"},"tanhyaBazeley":{"firstName":"Tanhya","lastName":"Bazeley","lat":52.5168396236,"long":13.5446436265,"personalityType":"INFJ","gender":"women"},"hildegaardCrosdill":{"firstName":"Hildegaard","lastName":"Crosdill","lat":52.5555229872,"long":13.2941773578,"personalityType":"INTP","gender":"o"},"silvainHinkes":{"firstName":"Silvain","lastName":"Hinkes","lat":52.5412926718,"long":13.2425157705,"personalityType":"ISFJ","gender":"men"},"cicelyIngyon":{"firstName":"Cicely","lastName":"Ingyon","lat":52.5461024657,"long":13.444826052,"personalityType":"ESTP","gender":"women"}}